__init__.py
__main__.py
application/__init__.py
application/app.py
task_5_python_package_by_ag-0.0.6.dist-info/METADATA
task_5_python_package_by_ag-0.0.6.dist-info/WHEEL
task_5_python_package_by_ag-0.0.6.dist-info/entry_points.txt
task_5_python_package_by_ag-0.0.6.dist-info/RECORD
