Metadata-Version: 2.1
Name: task_5_python_package_by_AG
Version: 0.0.6
Summary: The application counts the authentic characters in your string.
Author-email: Anton Galkin <anton.galkin@mail.ru>
Classifier: Operating System :: OS Independent
Classifier: Programming Language :: Python :: 3
Requires-Python: >=3.9
Requires-Dist: iniconfig>=2.0.0
Requires-Dist: packaging>=23.2
Requires-Dist: pluggy>=1.3.0
